{
    "history": "\n20130210T144937: Reformatted to NetCDF\nSolar data are written with 1 decimal precision although all the original data\nvalues are integers.\nObservation times were interpolated from the date-satellite-latitude lookup\ntable to the latitude vector with a cubic spline method.  The interpolated\nvector was then replicated across the grid for each longitude.  Observation\ntimes were written with 1 decimal precision for consistency with the lookup\ntable.\nSolar and Observation time data have a consistent no-data value of -999.\n", 
    "date_created": "unknown", 
    "date_modified": "20130210T144937", 
    "geospatial_lat_min": "-43.95", 
    "geospatial_lat_max": "-10.05", 
    "geospatial_lat_step": "0.05", 
    "geospatial_lat_units": "degrees_north", 
    "geospatial_lon_min": "112.05", 
    "geospatial_lon_max": "153.95", 
    "geospatial_lon_step": "0.05", 
    "geospatial_lon_units": "degrees_east", 
    "time_coverage_start": "1989-12-31T18Z", 
    "time_coverage_end": "1990-01-31T11Z", 
    "time_coverage_duration": "P1M", 
    "time_coverage_resolution": "PT1H", 
    "solar_dni:long_name": "Gridded hourly solar direct normal irradiance", 
    "solar_dni:standard_name": "surface_downwelling_shortwave_flux_in_air_due_to_direct_fraction", 
    "solar_dni:units": "W m-2", 
    "solar_dni:grid_mapping": "crs", 
    "solar_ghi:long_name": "Gridded hourly solar global horizontal irradiance", 
    "solar_ghi:standard_name": "surface_downwelling_shortwave_flux_in_air", 
    "solar_ghi:units": "W m-2", 
    "solar_ghi:grid_mapping": "crs", 
    "obs_time:long_name": "Interpolated instantaneous pixel observation time relative to time dimension value", 
    "obs_time:standard_name": "time", 
    "obs_time:units": "minutes", 
    "obs_time:grid_mapping": "crs", 
    "crs:grid_mapping_name": "latitude_longitude", 
    "crs:long_name": "WGS 1984 datum", 
    "crs:longitude_of_prime_meridian": "0.0", 
    "crs:semi_major_axis": "6378137.0", 
    "crs:inverse_flattening": "298.257223563"
}